llama_index/graph_rag/cognee/__init__.py
llama_index/graph_rag/cognee/base.py
llama_index/graph_rag/cognee/graph_rag.py
llama_index_graph_rag_cognee-0.2.0.dist-info/METADATA
llama_index_graph_rag_cognee-0.2.0.dist-info/WHEEL
llama_index_graph_rag_cognee-0.2.0.dist-info/licenses/LICENSE
llama_index_graph_rag_cognee-0.2.0.dist-info/RECORD
