Metadata-Version: 2.4
Name: llama-index-graph-rag-cognee
Version: 0.2.0
Summary: llama-index graph rag cognee integration
Author-email: Your Name <you@example.com>
License-Expression: MIT
License-File: LICENSE
Requires-Python: <4,>=3.10
Requires-Dist: cognee[neo4j,postgres,qdrant,weaviate]
Requires-Dist: httpx~=0.27.0
Requires-Dist: llama-index-core<0.14,>=0.13.0
